unicode_segment/__init__.py
unicode_segment/_rule_parser.py
unicode_segment/_segmenter.py
unicode_segment/_segmenter_config.py
unicode_segment/grapheme.py
unicode_segment/sentence.py
unicode_segment/word.py
unicode_segment-0.4.2.dist-info/licenses/LICENSE.txt
unicode_segment-0.4.2.dist-info/METADATA
unicode_segment-0.4.2.dist-info/WHEEL
unicode_segment-0.4.2.dist-info/top_level.txt
unicode_segment-0.4.2.dist-info/RECORD
