Metadata-Version: 2.4
Name: unicode-segment
Version: 0.4.2
Summary: Segment text with Unicode TR29-compliant segmenters.
Author-email: Lionel Rowe <lionel.rowe@gmail.com>
Maintainer-email: Lionel Rowe <lionel.rowe@gmail.com>
License: MIT License
Project-URL: Homepage, https://github.com/lionel-rowe/unicode-segment
Project-URL: Bug Reports, https://github.com/lionel-rowe/unicode-segment/issues
Project-URL: Source, https://github.com/lionel-rowe/unicode-segment/
Keywords: unicode,text-segmentation,segmenter,tr29,sentence,i18n
Classifier: Development Status :: 3 - Alpha
Classifier: Intended Audience :: Developers
Classifier: Operating System :: OS Independent
Classifier: Programming Language :: Python :: 3.9
Classifier: Programming Language :: Python :: 3.10
Classifier: Programming Language :: Python :: 3.11
Classifier: Programming Language :: Python :: 3.12
Classifier: Programming Language :: Python :: 3.13
Classifier: Programming Language :: Python :: 3.14
Classifier: Topic :: Text Processing
Classifier: Topic :: Text Processing :: General
Classifier: Topic :: Software Development :: Internationalization
Classifier: Topic :: Software Development :: Localization
Requires-Python: >=3.9
License-File: LICENSE.txt
Requires-Dist: regex>=2025.11.3
Dynamic: license-file
